[{"id":1, "number":1, "name":"1994", "company_id":1, "created_at":"2024-02-17 10:22:43", "updated_at":"2024-02-17 10:22:43"},
 {"id":2, "number":2, "name":"SIN ESPECIFICAR", "company_id":1, "created_at":"2024-02-17 10:22:43", "updated_at":"2024-02-17 10:22:43"},
 {"id":3, "number":3, "name":"2018", "company_id":1, "created_at":"2024-02-17 10:22:43", "updated_at":"2024-02-17 10:22:43"},
 {"id":4, "number":4, "name":"2016", "company_id":1, "created_at":"2024-02-17 10:22:43", "updated_at":"2024-02-17 10:22:43"},
 {"id":5, "number":5, "name":"2015", "company_id":1, "created_at":"2024-02-17 10:22:43", "updated_at":"2024-02-17 10:22:43"},
 {"id":6, "number":6, "name":"2013", "company_id":1, "created_at":"2024-02-17 10:22:43", "updated_at":"2024-02-17 10:22:43"},
 {"id":7, "number":7, "name":"2012", "company_id":1, "created_at":"2024-02-17 10:22:43", "updated_at":"2024-02-17 10:22:43"},
 {"id":8, "number":8, "name":"2020", "company_id":1, "created_at":"2024-03-09 04:03:41", "updated_at":"2024-03-09 04:03:41"}]